tightai/__init__.py
tightai/_nbdev.py
tightai/auth.py
tightai/base.py
tightai/cli.py
tightai/conf.py
tightai/core.py
tightai/downloaders.py
tightai/exceptions.py
tightai/handlers.py
tightai/local.py
tightai/lookup.py
tightai/projects.py
tightai/services.py
tightai/upload.py
tightai/user.py
tightai/utils.py
tightai-1.0.14.dist-info/LICENSE
tightai-1.0.14.dist-info/METADATA
tightai-1.0.14.dist-info/WHEEL
tightai-1.0.14.dist-info/entry_points.txt
tightai-1.0.14.dist-info/top_level.txt
tightai-1.0.14.dist-info/RECORD
