Metadata-Version: 2.1
Name: tightai
Version: 1.0.14
Summary: Serverless Model Hosting & Marketplace
Home-page: https://github.com/tightai/tightai
Author: Justin Mitchel
Author-email: hi@tight.ai
License: Apache Software License 2.0
Keywords: serverless ml,model hosting,ml marketplace,ai,machine learning
Platform: UNKNOWN
Classifier: Development Status :: 3 - Alpha
Classifier: Intended Audience :: Developers
Classifier: License :: OSI Approved :: Apache Software License
Classifier: Natural Language :: English
Classifier: Programming Language :: Python :: 3.6
Classifier: Programming Language :: Python :: 3.7
Classifier: Programming Language :: Python :: 3.8
Requires-Python: >=3.6
Requires-Dist: requests
Requires-Dist: pathspec
Requires-Dist: python-slugify
Requires-Dist: fastapi
Requires-Dist: uvicorn
Requires-Dist: python-multipart
Requires-Dist: fire
